<?xml version="1.0" encoding="utf-8"?>
<odoo>
    <data noupdate="1">
        <record id="mg_unloading_address_1" model="mg.unloading.address">
            <field name="name">Gedimino pr. 31, Vilnius</field>
        </record>
        <record id="mg_unloading_address_2" model="mg.unloading.address">
            <field name="name">Verkių g. 29, Vilnius</field>
        </record>
        <record id="mg_unloading_address_3" model="mg.unloading.address">
            <field name="name">Vokiečių g. 8, Vilnius</field>
        </record>
        <record id="mg_unloading_address_4" model="mg.unloading.address">
            <field name="name">Saltoniškių g. 9, Vilnius</field>
        </record>
        <record id="mg_unloading_address_5" model="mg.unloading.address">
            <field name="name">Gedimino g. 9, Vilnius</field>
        </record>
    </data>
</odoo>
